velocitas_lib/__init__.py
velocitas_lib/conan_utils.py
velocitas_lib/docker.py
velocitas_lib/file_utils.py
velocitas_lib/functional_interface.py
velocitas_lib/middleware.py
velocitas_lib/services.py
velocitas_lib/templates.py
velocitas_lib/text_utils.py
velocitas_lib/variables.py
velocitas_lib-0.0.13.dist-info/LICENSE
velocitas_lib-0.0.13.dist-info/METADATA
velocitas_lib-0.0.13.dist-info/NOTICE-3RD-PARTY-CONTENT.md
velocitas_lib-0.0.13.dist-info/NOTICE.md
velocitas_lib-0.0.13.dist-info/WHEEL
velocitas_lib-0.0.13.dist-info/top_level.txt
velocitas_lib-0.0.13.dist-info/RECORD
