Metadata-Version: 2.1
Name: velocitas-lib
Version: 0.0.13
License-File: LICENSE
License-File: NOTICE-3RD-PARTY-CONTENT.md
License-File: NOTICE.md
Requires-Dist: requests >=2.31.0
Requires-Dist: types-requests
